{
  "slides": [
    {
      "id": "slide_01",
      "title": "DOCSAM: UNIFIED DOCUMENT IMAGE SEGMENTATION VIA QUERY DECOMPOSITION AND HETEROGENEOUS MIXED LEARNING",
      "content": "Xiao-Hui Li¹, Fei Yin¹, Cheng-Lin Liu¹²\n¹MAIS, Institute of Automation, Chinese Academy of Sciences\n²School of Artificial Intelligence, University of Chinese Academy of Sciences\nEmail: {xiaohui.li, fyin, liucl}@nlpr.ia.ac.cn",
      "tables": [],
      "figures": []
    },
    {
      "id": "slide_02",
      "title": "目录",
      "content": "1. 研究背景与挑战\n2. DocSAM 模型架构设计\n3. 核心创新：语义查询与实例查询的交互机制\n4. 多任务统一训练与异构混合学习\n5. 实验结果与性能分析\n6. 总结与展望",
      "tables": [],
      "figures": []
    },
    {
      "id": "slide_03",
      "title": "研究背景与挑战",
      "content": "文档图像分割（DIS）是文档分析与识别（DAR）的核心任务，支撑文本识别、信息抽取和文档视觉问答等下游应用。然而，由于文档格式、布局结构和标注方式高度多样化（如现代PDF、历史文献、手写文档、表格、自然场景文本等），现有方法通常针对特定任务独立建模，导致模型碎片化、泛化能力差、资源开销大。本研究旨在构建一个统一、高效、可扩展的文档图像分割框架。",
      "tables": [],
      "figures": [
        {
          "fig_id": "fig_1",
          "figure_weight": 1292,
          "figure_height": 564
        }
      ]
    },
    {
      "id": "slide_04",
      "title": "DocSAM 模型整体架构",
      "content": "DocSAM 是一个基于 Transformer 的统一框架，将多种文档图像分割任务（如布局分析、多粒度文本检测、表格结构识别）统一为实例分割与语义分割的联合建模。其核心模块包括：视觉主干网络、可变形编码器、Sentence-BERT 文本编码器，以及提出的混合查询解码器（HQD）。模型支持通过自然语言输入类别名称进行灵活推理。",
      "tables": [],
      "figures": [
        {
          "fig_id": "fig_2",
          "figure_weight": 1239,
          "figure_height": 550
        }
      ]
    },
    {
      "id": "slide_05",
      "title": "核心创新：双查询交互机制",
      "content": "DocSAM 引入两类查询向量：\n- 实例查询（Instance Queries）：可学习的潜在向量，用于检测和分割每个实例；\n- 语义查询（Semantic Queries）：通过 Sentence-BERT 将类别名称嵌入到语义空间，作为‘提示’引导模型识别目标类别，并作为分类原型。\n两类查询在 HQD 中通过自注意力和交叉注意力机制充分交互，实现语义引导的实例分割与基于原型的分类（通过点积 + Softmax 实现）。",
      "tables": [],
      "figures": [
        {
          "fig_id": "fig_2",
          "figure_weight": 1239,
          "figure_height": 550
        }
      ]
    },
    {
      "id": "slide_06",
      "title": "异构混合学习：统一训练策略",
      "content": "DocSAM 能够在包含 48 个异构数据集的大规模混合数据上联合训练（见表1），涵盖文档布局、古籍/手写文档、表格识别和自然场景文本四大类任务。该设计使得单一模型具备跨任务、跨领域泛化能力。训练后，模型可直接作为通用分割器使用，也可无缝迁移到新任务进行微调，无需修改分类头，支持持续学习。",
      "tables": [
        {
          "table_id": "table_1",
          "table_weight": 1178,
          "table_height": 347
        }
      ],
      "figures": []
    },
    {
      "id": "slide_07",
      "title": "训练效率优化策略",
      "content": "为提升在大规模异构数据上的训练效率，DocSAM 采用三项关键技术：\n1. 使用 SimMIM 对视觉编码器进行预训练，增强特征鲁棒性；\n2. 采用课程学习（Curriculum Learning）策略，按任务相似性分组逐步引入数据；\n3. 提出实例查询选择（IQS）机制，在 HQD 层间动态筛选低分查询，显著减少计算开销而不影响性能。",
      "tables": [],
      "figures": [
        {
          "fig_id": "fig_3",
          "figure_weight": 1183,
          "figure_height": 372
        }
      ]
    },
    {
      "id": "slide_08",
      "title": "实验设置与评估指标",
      "content": "实验在 15 个代表性数据集上进行消融研究和微调验证，最终模型在全部 48 个数据集上训练。评估指标包括：\n- 实例分割：mAP、mAP_b（边界框）、mAF（多IoU阈值F-score）；\n- 语义分割：mIoU。\n模型提供两种尺寸：DocSAM-base（207M参数）和 DocSAM-large（317M参数）。",
      "tables": [],
      "figures": []
    },
    {
      "id": "slide_09",
      "title": "消融实验：关键组件有效性",
      "content": "表2显示各模块对性能的影响。移除查询交互或掩码注意力导致性能显著下降，证明其关键作用。课程学习提升收敛速度与最终性能，而实例查询选择（IQS）在不损失精度的前提下加快训练。使用更强的 Swin-large 主干网络进一步提升性能。",
      "tables": [
        {
          "table_id": "table_2",
          "table_weight": 620,
          "table_height": 252
        }
      ],
      "figures": []
    },
    {
      "id": "slide_10",
      "title": "预训练与微调性能对比",
      "content": "表3显示，DocSAM 在联合预训练后即在多个任务上表现良好。表4表明，在目标任务上微调后性能大幅提升，且显著优于从零训练的模型。在未见过的数据集（如 IIIT-AR-13K、CHDAC-2022）上微调也取得显著增益，验证了其强大的迁移能力。",
      "tables": [
        {
          "table_id": "table_3",
          "table_weight": 1242,
          "table_height": 525
        },
        {
          "table_id": "table_4",
          "table_weight": 1244,
          "table_height": 584
        }
      ],
      "figures": []
    },
    {
      "id": "slide_11",
      "title": "与前沿方法的性能对比",
      "content": "在 M6Doc 和 SCUT-CAB 数据集上，DocSAM 在实例检测 mAP 上达到最优（0.661 和 0.811），优于 Faster R-CNN、Mask R-CNN、Deformable DETR 等专用模型。在 CTW1500 和 Total-Text 场景文本检测任务上，DocSAM 表现尚可但不及专门设计的模型（如 DAT-SEG），说明在极端复杂文本场景下仍有提升空间。",
      "tables": [
        {
          "table_id": "table_5",
          "table_weight": 605,
          "table_height": 230
        },
        {
          "table_id": "table_6",
          "table_weight": 1008,
          "table_height": 231
        },
        {
          "table_id": "table_7",
          "table_weight": 589,
          "table_height": 253
        }
      ],
      "figures": []
    },
    {
      "id": "slide_12",
      "title": "定性结果展示",
      "content": "图4–图7展示了 DocSAM 在多种任务上的高质量预测结果，包括现代文档布局分析、古籍/手写文档分割、表格结构识别和自然场景文本检测。模型能准确识别并分割文本块、图表、表格单元格及任意形状文本，验证了其广泛适用性。",
      "tables": [],
      "figures": [
        {
          "fig_id": "fig_4",
          "figure_weight": 1319,
          "figure_height": 614
        },
        {
          "fig_id": "fig_5",
          "figure_weight": 1314,
          "figure_height": 612
        },
        {
          "fig_id": "fig_6",
          "figure_weight": 1314,
          "figure_height": 917
        },
        {
          "fig_id": "fig_7",
          "figure_weight": 1314,
          "figure_height": 1259
        }
      ]
    },
    {
      "id": "slide_13",
      "title": "失败案例分析",
      "content": "图8揭示了当前模型的局限性：\n1. 布局分析中存在过分割问题，尤其在大型表格单元格内含多段落时；\n2. 密集或弯曲文本行的边界框预测不精确；\n3. 场景文本检测中对密集、模糊、微小或遮挡文本的漏检较多。\n这些挑战提示未来需改进局部建模能力和数据增强策略。",
      "tables": [],
      "figures": [
        {
          "fig_id": "fig_8",
          "figure_weight": 1300,
          "figure_height": 1203
        }
      ]
    },
    {
      "id": "slide_14",
      "title": "结论与展望",
      "content": "DocSAM 提出了一种统一的文档图像分割框架，通过语义查询与实例查询的交互机制，实现了多任务、多数据集的联合建模。其优势在于：\n- 高泛化性与适应性；\n- 显著降低模型冗余与部署成本；\n- 支持持续学习与迁移微调。\n未来工作将探索多模态扩展（结合OCR文本）与更优训练策略，以进一步提升性能与收敛速度。代码已开源：https://github.com/xhli-git/DocSAM"
    }
  ]
}