[
  {
    "fig_id": "fig_1",
    "path": "output/NeuPL: Neural Population Learning_poster/visuals/images/fig_1.jpg",
    "caption": [
      "Transitive Skills "
    ],
    "content_list_index": 3
  },
  {
    "fig_id": "fig_2",
    "path": "output/NeuPL: Neural Population Learning_poster/visuals/images/fig_2.jpg",
    "caption": [
      "Strategic Cycles "
    ],
    "content_list_index": 4
  },
  {
    "fig_id": "fig_3",
    "path": "output/NeuPL: Neural Population Learning_poster/visuals/images/fig_3.jpg",
    "caption": [
      "Game-of-Skills "
    ],
    "content_list_index": 5
  },
  {
    "fig_id": "fig_4",
    "path": "output/NeuPL: Neural Population Learning_poster/visuals/images/fig_4.jpg",
    "caption": [],
    "content_list_index": 9
  },
  {
    "fig_id": "fig_5",
    "path": "output/NeuPL: Neural Population Learning_poster/visuals/images/fig_5.jpg",
    "caption": [],
    "content_list_index": 10
  },
  {
    "fig_id": "fig_6",
    "path": "output/NeuPL: Neural Population Learning_poster/visuals/images/fig_6.jpg",
    "caption": [],
    "content_list_index": 11
  },
  {
    "fig_id": "fig_7",
    "path": "output/NeuPL: Neural Population Learning_poster/visuals/images/fig_7.jpg",
    "caption": [],
    "content_list_index": 12
  },
  {
    "fig_id": "fig_8",
    "path": "output/NeuPL: Neural Population Learning_poster/visuals/images/fig_8.jpg",
    "caption": [
      "Fictitious Play "
    ],
    "content_list_index": 15
  },
  {
    "fig_id": "fig_9",
    "path": "output/NeuPL: Neural Population Learning_poster/visuals/images/fig_9.jpg",
    "caption": [
      "PSRO-NASH "
    ],
    "content_list_index": 16
  },
  {
    "fig_id": "fig_10",
    "path": "output/NeuPL: Neural Population Learning_poster/visuals/images/fig_10.jpg",
    "caption": [],
    "content_list_index": 19
  },
  {
    "fig_id": "fig_11",
    "path": "output/NeuPL: Neural Population Learning_poster/visuals/images/fig_11.jpg",
    "caption": [],
    "content_list_index": 20
  },
  {
    "fig_id": "fig_12",
    "path": "output/NeuPL: Neural Population Learning_poster/visuals/images/fig_12.jpg",
    "caption": [],
    "content_list_index": 25
  },
  {
    "fig_id": "fig_13",
    "path": "output/NeuPL: Neural Population Learning_poster/visuals/images/fig_13.jpg",
    "caption": [],
    "content_list_index": 26
  },
  {
    "fig_id": "fig_14",
    "path": "output/NeuPL: Neural Population Learning_poster/visuals/images/fig_14.jpg",
    "caption": [],
    "content_list_index": 27
  },
  {
    "fig_id": "fig_15",
    "path": "output/NeuPL: Neural Population Learning_poster/visuals/images/fig_15.jpg",
    "caption": [],
    "content_list_index": 29
  },
  {
    "fig_id": "fig_16",
    "path": "output/NeuPL: Neural Population Learning_poster/visuals/images/fig_16.jpg",
    "caption": [],
    "content_list_index": 30
  },
  {
    "fig_id": "fig_17",
    "path": "output/NeuPL: Neural Population Learning_poster/visuals/images/fig_17.jpg",
    "caption": [],
    "content_list_index": 31
  },
  {
    "fig_id": "fig_18",
    "path": "output/NeuPL: Neural Population Learning_poster/visuals/images/fig_18.jpg",
    "caption": [],
    "content_list_index": 32
  },
  {
    "fig_id": "fig_19",
    "path": "output/NeuPL: Neural Population Learning_poster/visuals/images/fig_19.jpg",
    "caption": [],
    "content_list_index": 33
  },
  {
    "fig_id": "fig_20",
    "path": "output/NeuPL: Neural Population Learning_poster/visuals/images/fig_20.jpg",
    "caption": [],
    "content_list_index": 34
  },
  {
    "fig_id": "fig_21",
    "path": "output/NeuPL: Neural Population Learning_poster/visuals/images/fig_21.jpg",
    "caption": [],
    "content_list_index": 35
  },
  {
    "fig_id": "fig_22",
    "path": "output/NeuPL: Neural Population Learning_poster/visuals/images/fig_22.jpg",
    "caption": [],
    "content_list_index": 36
  },
  {
    "fig_id": "fig_23",
    "path": "output/NeuPL: Neural Population Learning_poster/visuals/images/fig_23.jpg",
    "caption": [],
    "content_list_index": 37
  },
  {
    "fig_id": "fig_24",
    "path": "output/NeuPL: Neural Population Learning_poster/visuals/images/fig_24.jpg",
    "caption": [],
    "content_list_index": 38
  },
  {
    "fig_id": "fig_25",
    "path": "output/NeuPL: Neural Population Learning_poster/visuals/images/fig_25.jpg",
    "caption": [],
    "content_list_index": 39
  },
  {
    "fig_id": "fig_26",
    "path": "output/NeuPL: Neural Population Learning_poster/visuals/images/fig_26.jpg",
    "caption": [],
    "content_list_index": 40
  },
  {
    "fig_id": "fig_27",
    "path": "output/NeuPL: Neural Population Learning_poster/visuals/images/fig_27.jpg",
    "caption": [],
    "content_list_index": 41
  },
  {
    "fig_id": "fig_28",
    "path": "output/NeuPL: Neural Population Learning_poster/visuals/images/fig_28.jpg",
    "caption": [],
    "content_list_index": 42
  },
  {
    "fig_id": "fig_29",
    "path": "output/NeuPL: Neural Population Learning_poster/visuals/images/fig_29.jpg",
    "caption": [],
    "content_list_index": 43
  },
  {
    "fig_id": "fig_30",
    "path": "output/NeuPL: Neural Population Learning_poster/visuals/images/fig_30.jpg",
    "caption": [],
    "content_list_index": 44
  },
  {
    "fig_id": "fig_31",
    "path": "output/NeuPL: Neural Population Learning_poster/visuals/images/fig_31.jpg",
    "caption": [],
    "content_list_index": 45
  },
  {
    "fig_id": "fig_32",
    "path": "output/NeuPL: Neural Population Learning_poster/visuals/images/fig_32.jpg",
    "caption": [],
    "content_list_index": 47
  },
  {
    "fig_id": "fig_33",
    "path": "output/NeuPL: Neural Population Learning_poster/visuals/images/fig_33.jpg",
    "caption": [],
    "content_list_index": 48
  },
  {
    "fig_id": "fig_34",
    "path": "output/NeuPL: Neural Population Learning_poster/visuals/images/fig_34.jpg",
    "caption": [],
    "content_list_index": 49
  },
  {
    "fig_id": "fig_35",
    "path": "output/NeuPL: Neural Population Learning_poster/visuals/images/fig_35.jpg",
    "caption": [],
    "content_list_index": 51
  }
]